noahs_raspberry_pi_python_ide/__init__.py
noahs_raspberry_pi_python_ide/pi_code_editor.py
noahs_raspberry_pi_python_ide-0.1.0.dist-info/METADATA
noahs_raspberry_pi_python_ide-0.1.0.dist-info/WHEEL
noahs_raspberry_pi_python_ide-0.1.0.dist-info/top_level.txt
noahs_raspberry_pi_python_ide-0.1.0.dist-info/RECORD
